dhanhq/__init__.py
dhanhq/dhanhq.py
dhanhq/marketfeed.py
dhanhq/orderupdate.py
dhanhq_qpython-2.0.2.dist-info/METADATA
dhanhq_qpython-2.0.2.dist-info/WHEEL
dhanhq_qpython-2.0.2.dist-info/top_level.txt
dhanhq_qpython-2.0.2.dist-info/RECORD
